[
  {
    "name": "Being Balatro",
    "points": 2602112
  },
  {
    "name": "IO",
    "points": 1030168
  },
  {
    "name": "El viniador",
    "points": 55293
  },
  {
    "name": "Sara Satanasso",
    "points": 33089
  },
  {
    "name": "Controego",
    "points": 33060.43
  },
  {
    "name": "dannyell44y",
    "points": 32012
  },
  {
    "name": "Jonny joneve",
    "points": 29700
  },
  {
    "name": "Calamaro88",
    "points": 25605.3
  },
  {
    "name": "Clippy",
    "points": 22959
  },
  {
    "name": "Mario \"x\" De Angelis",
    "points": 20270
  },
  {
    "name": "Steamlore",
    "points": 16499
  },
  {
    "name": "MSI Katana",
    "points": 16040
  },
  {
    "name": "Fadaniele",
    "points": 14500
  },
  {
    "name": "Gian (skino)",
    "points": 14403
  },
  {
    "name": "Trilobox",
    "points": 13340
  },
  {
    "name": "Mars",
    "points": 22265.999999
  },
  {
    "name": "Bonsen",
    "points": 8610
  },
  {
    "name": "Alberto Cocco",
    "points": 8608
  },
  {
    "name": "Uomotelis",
    "points": 8400
  },
  {
    "name": "Andrea",
    "points": 8294
  },
  {
    "name": "Ylias",
    "points": 8000
  },
  {
    "name": "Jobin",
    "points": 7636
  },
  {
    "name": "Sapone",
    "points": 5800
  },
  {
    "name": "Francesco El guapo",
    "points": 5640
  },
  {
    "name": "Diego monsneagu",
    "points": 5400
  },
  {
    "name": "Samu",
    "points": 5146
  },
  {
    "name": "Giuliozzz",
    "points": 5101
  },
  {
    "name": "Amon",
    "points": 5000
  },
  {
    "name": "Gabriele Cactus",
    "points": 4980.3
  },
  {
    "name": "Sapo",
    "points": 4269
  },
  {
    "name": "ale luna",
    "points": 4200
  },
  {
    "name": "Mirko",
    "points": 3000
  },
  {
    "name": "Fabrizio Biagioli",
    "points": 2500
  },
  {
    "name": "Sara",
    "points": 2400
  },
  {
    "name": "Giuseppe Dara",
    "points": 2300
  },
  {
    "name": "Lorenzo bloodborne",
    "points": 2200
  },
  {
    "name": "Aemlacking",
    "points": 12100
  },
  {
    "name": "Simone Luba",
    "points": 1515
  },
  {
    "name": "Marco",
    "points": 1340
  },
  {
    "name": "Violetta",
    "points": 1300
  },
  {
    "name": "Fendro",
    "points": 1269
  },
  {
    "name": "Grobbi",
    "points": 1099
  },
  {
    "name": "Daniele Leone",
    "points": 1002
  },
  {
    "name": "Edoardo",
    "points": 1000
  },
  {
    "name": "ricky_",
    "points": 750
  },
  {
    "name": "Peter Parker",
    "points": 740
  },
  {
    "name": "Peter palle",
    "points": 700
  },
  {
    "name": "ObbaigMaria",
    "points": 666
  },
  {
    "name": "Aurelio",
    "points": 420
  },
  {
    "name": "Miao miao susina miao",
    "points": 403
  },
  {
    "name": "Nessuno",
    "points": 273
  },
  {
    "name": "Francio",
    "points": 219
  },
  {
    "name": "duca gott",
    "points": 120
  },
  {
    "name": "Shinji (Angelo)",
    "points": 104
  },
  {
    "name": "Nicola V",
    "points": 27
  },
  {
    "name": "Damiano Martini",
    "points": 13
  },
  {
    "name": "Giorgio",
    "points": 13
  },
  {
    "name": "Legoshi",
    "points": 12.927
  },
  {
    "name": "Angelo",
    "points": 12
  },
  {
    "name": "Ale",
    "points": 10
  },
  {
    "name": "Barbara",
    "points": 1
  },
  {
    "name": "Dario Moccia",
    "points": 0.52
  },
  {
    "name": "franliu",
    "points": 0.1
  },
  {
    "name": "Giovanni Bruno",
    "points": null
  },
  {
    "name": "Argomanto",
    "points": -2
  },
  {
    "name": "Maxi formato",
    "points": -21
  },
  {
    "name": "slime",
    "points": -56
  },
  {
    "name": "Carmelo Simone C.",
    "points": -172
  },
  {
    "name": "Sigghe",
    "points": -202
  },
  {
    "name": "Teo",
    "points": -600
  },
  {
    "name": "Barbie",
    "points": -1500
  },
  {
    "name": "Maya",
    "points": -2262
  },
  {
    "name": "Diego mosneagu",
    "points": -3400
  },
  {
    "name": "Giamcoo",
    "points": -848380
  },
  {
    "name": "Ric utente nulla tenete",
    "points": -15996001
  }
]
